metacycle_core/__init__.py
metacycle_core/bluetooth.py
metacycle_core/carla_interface.py
metacycle_core/filters.py
metacycle_core/hello.py
metacycle_core-0.1.14.dist-info/METADATA
metacycle_core-0.1.14.dist-info/WHEEL
metacycle_core-0.1.14.dist-info/entry_points.txt
metacycle_core-0.1.14.dist-info/top_level.txt
metacycle_core-0.1.14.dist-info/RECORD
