Metadata-Version: 2.2
Name: metacycle-core
Version: 0.1.14
Summary: python backend server for metacycle, interacting with bluetooth accessories and controlling carla simulator.
Requires-Python: ~=3.10
Requires-Dist: aiohttp-cors>=0.7.0
Requires-Dist: aiohttp>=3.11.11
Requires-Dist: python-socketio>=5.12.1
Requires-Dist: bleak>=0.22.3
Requires-Dist: rich>=13.9.4
Requires-Dist: carla==0.9.15
Requires-Dist: pygame>=2.6.1
Requires-Dist: numpy>=2.2.2
Requires-Dist: opencv-python>=4.11.0.86
